plenario_core/__init__.py
plenario_core/admin.py
plenario_core/apps.py
plenario_core/defaults.py
plenario_core/deserializers.py
plenario_core/enums.py
plenario_core/fields.py
plenario_core/managers.py
plenario_core/mixins.py
plenario_core/models.py
plenario_core/schemas.py
plenario_core/serializers.py
plenario_core/services.py
plenario_core/signals.py
plenario_core/validators.py
plenario_core/migrations/__init__.py
plenario_core/utils/__init__.py
plenario_core/utils/dynamic_models.py
plenario_core/utils/field_parsing.py
plenario_core/utils/postgres/__init__.py
plenario_core/utils/postgres/common.py
plenario_core/utils/postgres/date_triggers.py
plenario_core/utils/postgres/geo_triggers.py
plenario_core/utils/postgres/sql/create-trigger.sql.template
plenario_core/utils/postgres/sql/insert-point.sql.template
plenario_core/utils/postgres/sql/insert-timestamp.sql.template
plenario_core/utils/postgres/sql/parse-point-location.sql.template
plenario_core/utils/postgres/sql/parse-point-long-lat.sql.template
plenario_core/utils/postgres/sql/parse-timestamp.sql.template
plenario_core/views/__init__.py
plenario_core/views/bases.py
plenario_core/views/export.py
plenario_core/views/meta_generic.py
plenario_core/views/search.py
plenario_core-0.0.15.dist-info/DESCRIPTION.rst
plenario_core-0.0.15.dist-info/METADATA
plenario_core-0.0.15.dist-info/RECORD
plenario_core-0.0.15.dist-info/WHEEL
plenario_core-0.0.15.dist-info/metadata.json
plenario_core-0.0.15.dist-info/top_level.txt
