Metadata-Version: 2.0
Name: plenario-core
Version: 0.0.15
Summary: abstract bases for plenario
Home-page: https://github.com/UrbanCCD-UChicago/plenario-core
Author: Vince Forgione
Author-email: vforgione@uhicago.edu
License: GPLv3
Keywords: plenario
Platform: UNKNOWN
Classifier: Development Status :: 3 - Alpha
Classifier: License :: OSI Approved :: GNU General Public License v3 (GPLv3)
Classifier: Programming Language :: Python :: 3.6
Requires-Python: >=3.6
Requires-Dist: arrow
Requires-Dist: Django (<1.12,>=1.11)
Requires-Dist: django-fsm
Requires-Dist: marshmallow
Requires-Dist: psycopg2
